sneks/__init__.py
sneks/engine/__init__.py
sneks/engine/config/__init__.py
sneks/engine/config/definition.py
sneks/engine/config/instantiation.py
sneks/engine/core/__init__.py
sneks/engine/core/cell.py
sneks/engine/core/direction.py
sneks/engine/engine/__init__.py
sneks/engine/engine/cells.py
sneks/engine/engine/mover.py
sneks/engine/engine/registrar.py
sneks/engine/engine/runner.py
sneks/engine/engine/state.py
sneks/engine/gui/__init__.py
sneks/engine/gui/graphics.py
sneks/engine/gui/poster.py
sneks/engine/gui/recorder.py
sneks/engine/interface/__init__.py
sneks/engine/interface/snek.py
sneks/engine/validator/__init__.py
sneks/engine/validator/main.py
sneks/engine/validator/test_existance.py
sneks/engine/validator/test_functionality.py
toroidal_sneks-1.0.3.dist-info/LICENSE
toroidal_sneks-1.0.3.dist-info/METADATA
toroidal_sneks-1.0.3.dist-info/WHEEL
toroidal_sneks-1.0.3.dist-info/entry_points.txt
toroidal_sneks-1.0.3.dist-info/top_level.txt
toroidal_sneks-1.0.3.dist-info/RECORD
